{"create_model/Accuracy": 0.9793, "create_model/AUC": 0.9064, "create_model/Recall": 0.38, "create_model/Prec.": 0.6015, "create_model/F1": 0.4206, "create_model/Kappa": 0.4114, "create_model/MCC": 0.4432, "create_model/TT": 0.52, "_timestamp": 1689733288.0297449, "_runtime": 25.32736897468567, "_step": 4, "AUC": {"_type": "image-file", "sha256": "6462dfda899c9a5f8d5a029d5b812c303dd3d459a2a39f3e3280090bb37d0fba", "size": 73693, "path": "media/images/AUC_1_6462dfda899c9a5f8d5a.png", "format": "png", "width": 698, "height": 507}, "Confusion Matrix": {"_type": "image-file", "sha256": "a414075f6c20add0bb3f965f840e40c059bbd549a3d06d56d6a125f04667a577", "size": 15608, "path": "media/images/Confusion Matrix_2_a414075f6c20add0bb3f.png", "format": "png", "width": 784, "height": 534}, "Feature Importance": {"_type": "image-file", "sha256": "928845ca20be2d5b8c8ae9d38af14fc387ee4953d300dd4e5de0967915288368", "size": 55524, "path": "media/images/Feature Importance_3_928845ca20be2d5b8c8a.png", "format": "png", "width": 920, "height": 468}, "shap_values": {"_type": "image-file", "sha256": "cefaabc484518c3fb12d74f7fa4dae43014bd577800887eb113ec07ee2117ada", "size": 158293, "path": "media/images/shap_values_4_cefaabc484518c3fb12d.png", "format": "png", "width": 792, "height": 934}, "_wandb": {"runtime": 24}}